postal/__init__.py
postal/client.py
postal/mq.py
postal/server.py
postal_mcp-0.1.0.dist-info/licenses/LICENSE.md
postal_mcp-0.1.0.dist-info/METADATA
postal_mcp-0.1.0.dist-info/WHEEL
postal_mcp-0.1.0.dist-info/entry_points.txt
postal_mcp-0.1.0.dist-info/top_level.txt
postal_mcp-0.1.0.dist-info/RECORD
