Metadata-Version: 2.4
Name: postal-mcp
Version: 0.1.0
Summary: A mailbox system for MCP, so that two agents can chat
Author-email: Tim Kellogg <timothy.kellogg@gmail.com>
License-Expression: Apache-2.0
Project-URL: Homepage, https://github.com/tkellogg/postal-mcp
Project-URL: Bug Tracker, https://github.com/tkellogg/postal-mcp/issues
Requires-Python: >=3.12
License-File: LICENSE.md
Requires-Dist: aiosqlite>=0.21.0
Requires-Dist: fastapi>=0.115.14
Requires-Dist: fastmcp>=2.9.2
Requires-Dist: uvicorn>=0.34.3
Dynamic: license-file
